vercompare/__init__.py
vercompare/compare.py
pyvercompare-0.2.1.dist-info/METADATA
pyvercompare-0.2.1.dist-info/WHEEL
pyvercompare-0.2.1.dist-info/top_level.txt
pyvercompare-0.2.1.dist-info/RECORD
