Metadata-Version: 2.1
Name: pyvercompare
Version: 0.2.1
Summary: Compare versions of strings
Author: Scott Walsh
Author-email: scott@invisiblethreat.ca
Maintainer: Scott Walsh
Maintainer-email: scott@invisiblethreat.ca
Project-URL: documentation, https://github.com/invisiblethreat/pyvercompare/blob/main/README.md
Project-URL: repository, https://github.com/invisiblethreat/pyvercompare
Project-URL: homepage, https://github.com/invisiblethreat/pyvercompare
Keywords: compare,strings
Classifier: Development Status :: 4 - Beta
Classifier: Programming Language :: Python
Requires-Python: >=3.7
